qtforms/__init__.py
qtforms/form.py
qtforms/labeled_registry.py
qtforms/protocols.py
qtforms/widgets/labeled.py
qtforms/wrappers.py
qtforms-0.1.0.dist-info/METADATA
qtforms-0.1.0.dist-info/WHEEL
qtforms-0.1.0.dist-info/RECORD
