Metadata-Version: 2.1
Name: qtforms
Version: 0.1.0
Summary: pydantic powered forms for Qt
Author: jhnnsrs
Author-email: jhnnsrs@gmail.com
Requires-Python: >=3.8
Classifier: Programming Language :: Python :: 3
Classifier: Programming Language :: Python :: 3.8
Classifier: Programming Language :: Python :: 3.9
Classifier: Programming Language :: Python :: 3.10
Classifier: Programming Language :: Python :: 3.11
Requires-Dist: pydantic (<2)
Requires-Dist: qtpy (>=2.4.1,<3.0.0)
